LICENSE
MANIFEST.in
README.rst
pyproject.toml
setup.py
python/SQNomad/__init__.py
python/SQNomad/_nomad.py
python/SQNomad/_version.py
python/SQNomad.egg-info/PKG-INFO
python/SQNomad.egg-info/SOURCES.txt
python/SQNomad.egg-info/dependency_links.txt
python/SQNomad.egg-info/not-zip-safe
python/SQNomad.egg-info/requires.txt
python/SQNomad.egg-info/top_level.txt
src/config.hpp
src/nomad_nsbegin.hpp
src/nomad_nsend.hpp
src/nomad_version.hpp
src/Algos/AlgoStopReasons.cpp
src/Algos/AlgoStopReasons.hpp
src/Algos/Algorithm.cpp
src/Algos/Algorithm.hpp
src/Algos/CacheInterface.cpp
src/Algos/CacheInterface.hpp
src/Algos/EvcInterface.cpp
src/Algos/EvcInterface.hpp
src/Algos/Initialization.cpp
src/Algos/Initialization.hpp
src/Algos/Iteration.cpp
src/Algos/Iteration.hpp
src/Algos/IterationUtils.cpp
src/Algos/IterationUtils.hpp
src/Algos/MainStep.cpp
src/Algos/MainStep.hpp
src/Algos/MegaIteration.cpp
src/Algos/MegaIteration.hpp
src/Algos/MeshBase.cpp
src/Algos/MeshBase.hpp
src/Algos/Projection.cpp
src/Algos/Projection.hpp
src/Algos/Step.cpp
src/Algos/Step.hpp
src/Algos/Subproblem.cpp
src/Algos/Subproblem.hpp
src/Algos/SubproblemManager.cpp
src/Algos/SubproblemManager.hpp
src/Algos/Termination.cpp
src/Algos/Termination.hpp
src/Algos/LatinHypercubeSampling/LH.cpp
src/Algos/LatinHypercubeSampling/LH.hpp
src/Algos/Mads/DoublePollMethod.cpp
src/Algos/Mads/DoublePollMethod.hpp
src/Algos/Mads/GMesh.cpp
src/Algos/Mads/GMesh.hpp
src/Algos/Mads/LHSearchMethod.cpp
src/Algos/Mads/LHSearchMethod.hpp
src/Algos/Mads/Mads.cpp
src/Algos/Mads/Mads.hpp
src/Algos/Mads/MadsInitialization.cpp
src/Algos/Mads/MadsInitialization.hpp
src/Algos/Mads/MadsIteration.cpp
src/Algos/Mads/MadsIteration.hpp
src/Algos/Mads/MadsMegaIteration.cpp
src/Algos/Mads/MadsMegaIteration.hpp
src/Algos/Mads/MadsUpdate.cpp
src/Algos/Mads/MadsUpdate.hpp
src/Algos/Mads/MegaSearchPoll.cpp
src/Algos/Mads/MegaSearchPoll.hpp
src/Algos/Mads/NMSearchMethod.cpp
src/Algos/Mads/NMSearchMethod.hpp
src/Algos/Mads/NP1UniPollMethod.cpp
src/Algos/Mads/NP1UniPollMethod.hpp
src/Algos/Mads/Ortho2NPollMethod.cpp
src/Algos/Mads/Ortho2NPollMethod.hpp
src/Algos/Mads/Poll.cpp
src/Algos/Mads/Poll.hpp
src/Algos/Mads/PollMethodBase.cpp
src/Algos/Mads/PollMethodBase.hpp
